sentimentAnalizis/Token.py
sentimentAnalizis/Trie.py
sentimentAnalizis/__init__.py
sentimentAnalizis/parser.py
sentimentAnalizis/utils.py
sentimentAnalizis/datasetParsers/__init__.py
sentimentAnalizis/datasetParsers/leIA.py
sentimentAnalizis/datasetParsers/linguaKit.py
sentimentAnalizis/datasetParsers/parse.py
sentimentAnalizis/datasetParsers/sentilex.py
sentimentAnalizis/datasetParsers/utils.py
sentimentAnalizis/datasets/boosters.json
sentimentAnalizis/datasets/emojis.json
sentimentAnalizis/datasets/emojis.txt
sentimentAnalizis/datasets/lemmas.json
sentimentAnalizis/datasets/multiplier.txt
sentimentAnalizis/datasets/negate.json
sentimentAnalizis/datasets/words.json
sentimentAnalizis/datasets/LinguaKit/lex.txt
sentimentAnalizis/datasets/LinguaKit/train.txt
sentimentAnalizis/datasets/leIA/booster.txt
sentimentAnalizis/datasets/leIA/emojis.txt
sentimentAnalizis/datasets/leIA/negate.txt
sentimentAnalizis/datasets/leIA/vader_lexicon.txt
sentimentAnalizis/datasets/sentilex/sentilex.txt
sentimentAnalizis/tests/txt
sentimentanalizis-1.0.0.dist-info/entry_points.txt
sentimentanalizis-1.0.0.dist-info/WHEEL
sentimentanalizis-1.0.0.dist-info/METADATA
sentimentanalizis-1.0.0.dist-info/RECORD
